MANIFEST.in
README.rst
setup.py
django_reportengine.egg-info/PKG-INFO
django_reportengine.egg-info/SOURCES.txt
django_reportengine.egg-info/dependency_links.txt
django_reportengine.egg-info/not-zip-safe
django_reportengine.egg-info/top_level.txt
reportengine/__init__.py
reportengine/base.py
reportengine/filtercontrols.py
reportengine/jsonfield.py
reportengine/models.py
reportengine/outputformats.py
reportengine/settings.py
reportengine/tasks.py
reportengine/tests.py
reportengine/urls.py
reportengine/views.py
reportengine/management/__init__.py
reportengine/management/commands/__init__.py
reportengine/management/commands/cleanup_stale_reports.py
reportengine/management/commands/generate_report.py
reportengine/templates/reportengine/async_wait.html
reportengine/templates/reportengine/calendar.html
reportengine/templates/reportengine/calendar_day.html
reportengine/templates/reportengine/calendar_month.html
reportengine/templates/reportengine/list.html
reportengine/templates/reportengine/report.html
reportengine/templates/reportengine/request_report.html