Metadata-Version: 1.1
Name: django-reportengine
Version: 0.3.0
Summary: A Django app for building and integrating reports into your Django project.
Home-page: http://github.com/cuker/django-reportengine
Author: Nikolaj Baer
Author-email: nikolaj@cukerinteractive.com
License: MIT License
Keywords: django reporting reports
Platform: UNKNOWN
Classifier: Programming Language :: Python
Classifier: Operating System :: OS Independent
Classifier: Natural Language :: English
Classifier: Development Status :: 4 - Beta
Classifier: Intended Audience :: Developers
Classifier: Topic :: Internet :: WWW/HTTP :: Dynamic Content
